entelecheia/__cli__.py
entelecheia/__init__.py
entelecheia/_version.py
entelecheia/py.typed
entelecheia/conf/__init__.py
entelecheia/conf/about/entelecheia.yaml
entelecheia-0.3.6.dist-info/METADATA
entelecheia-0.3.6.dist-info/WHEEL
entelecheia-0.3.6.dist-info/entry_points.txt
entelecheia-0.3.6.dist-info/licenses/LICENSE
entelecheia-0.3.6.dist-info/RECORD
