Metadata-Version: 2.4
Name: entelecheia
Version: 0.3.6
Summary: ἐντελέχεια is coined by Aristotle from ἐντελής (entelḗs, "complete, full, accomplished") + ἔχειν (ékhein, "have, hold").
Author-email: Young Joon Lee <entelecheia@hotmail.com>
License: MIT
License-File: LICENSE
Requires-Python: <3.13,>=3.9
Provides-Extra: dev
Requires-Dist: black>=24.0.0; extra == 'dev'
Requires-Dist: flake8-pyproject>=1.2.2; extra == 'dev'
Requires-Dist: flake8>=6.0.0; extra == 'dev'
Requires-Dist: isort>=5.12.0; extra == 'dev'
Requires-Dist: mypy>=1.0.0; extra == 'dev'
Requires-Dist: pytest-cov>=4.0.0; extra == 'dev'
Requires-Dist: pytest>=7.2.1; extra == 'dev'
Requires-Dist: python-semantic-release>=9.0.0; extra == 'dev'
